BoschRpaMagicBox/__init__.py
BoschRpaMagicBox/common_config.py
BoschRpaMagicBox/common_functions.py
BoschRpaMagicBox/data_process_functions.py
BoschRpaMagicBox/database_functions.py
BoschRpaMagicBox/esm_api_functions.py
BoschRpaMagicBox/helper_functions.py
BoschRpaMagicBox/outlook_reader_manager.py
BoschRpaMagicBox/printer_manager.py
BoschRpaMagicBox/remote_excel_functions.py
BoschRpaMagicBox/sharepoint_manager.py
BoschRpaMagicBox/smb_functions.py
BoschRpaMagicBox/smb_functions_manager.py
boschrpamagicbox-0.2.115.dist-info/licenses/LICENSE
boschrpamagicbox-0.2.115.dist-info/METADATA
boschrpamagicbox-0.2.115.dist-info/WHEEL
boschrpamagicbox-0.2.115.dist-info/top_level.txt
boschrpamagicbox-0.2.115.dist-info/RECORD
