Metadata-Version: 2.4
Name: BoschRpaMagicBox
Version: 0.2.115
Summary: This package is used for building automation functions for rpa within Bosch
Author-email: LV Zhichao <zhichao.lv@cn.bosch.com>
Project-URL: Homepage, https://github.boschdevcloud.com/LZV2SZH/BoschRpaMagicBox
Project-URL: Bug Tracker, https://github.boschdevcloud.com/LZV2SZH/BoschRpaMagicBox/issues
Classifier: Programming Language :: Python :: 3
Classifier: License :: OSI Approved :: MIT License
Classifier: Operating System :: OS Independent
Requires-Python: >=3.6
License-File: LICENSE
Requires-Dist: pyperclip
Requires-Dist: selenium==4.8.0
Requires-Dist: openpyxl
Requires-Dist: xlrd==2.0.1
Requires-Dist: smbprotocol
Requires-Dist: requests
Requires-Dist: pymysql
Requires-Dist: pandas
Requires-Dist: xlsx2html
Requires-Dist: weasyprint
Requires-Dist: beautifulsoup4
Requires-Dist: lxml
Requires-Dist: pdfplumber
Requires-Dist: Office365-REST-Python-Client
Requires-Dist: msal
Requires-Dist: python-magic
Requires-Dist: requests_ntlm
Requires-Dist: PyMuPDF==1.25.5
Dynamic: license-file
